{
  "id": "sublime-text/packages",
  "title": "Packages",
  "description": "Install Package Control",
  "source": "@site/docs/sublime-text/packages.md",
  "sourceDirName": "sublime-text",
  "slug": "/sublime-text/packages",
  "permalink": "/mac-setup/sublime-text/packages",
  "draft": false,
  "unlisted": false,
  "editUrl": "https://github.com/sb2nov/mac-setup/tree/main/docs/sublime-text/packages.md",
  "tags": [],
  "version": "current",
  "frontMatter": {
    "title": "Packages"
  },
  "sidebar": "tutorialSidebar",
  "previous": {
    "title": "Preferences",
    "permalink": "/mac-setup/sublime-text/preferences"
  },
  "next": {
    "title": "Plugins",
    "permalink": "/mac-setup/sublime-text/plugins"
  }
}